{
  "usingComponents": {
    "navbar": "/components/navbar/index",
    "goodList": "/components/goodList/index",
    "promotionGood": "/components/promotionGood/index",
    "coupon-window": "/components/coupon-window/index",
    "home": "/components/home/index"
  },
    "navigationBarBackgroundColor": "#3BA4EA",
    "navigationBarTextStyle": "white",
    "navigationBarTitleText": "伟星商城",
    "backgroundColor": "#eeeeee",
    "backgroundTextStyle": "light",
    "enablePullDownRefresh": false,
    "navigationStyle":"default"
}